retinaface/__init__.py
retinaface/convert_to_onnx.py
retinaface/detect.py
retinaface/inference_framework.py
retinaface/test_fddb.py
retinaface/test_widerface.py
retinaface/train.py
retinaface/data/__init__.py
retinaface/data/config.py
retinaface/data/data_augment.py
retinaface/data/wider_face.py
retinaface/layers/__init__.py
retinaface/layers/functions/__init__.py
retinaface/layers/functions/prior_box.py
retinaface/layers/modules/__init__.py
retinaface/layers/modules/multibox_loss.py
retinaface/models/__init__.py
retinaface/models/net.py
retinaface/models/retinaface.py
retinaface/utils/__init__.py
retinaface/utils/box_utils.py
retinaface/utils/timer.py
retinaface/utils/nms/__init__.py
retinaface/utils/nms/py_cpu_nms.py
retinaface/widerface_evaluate/__init__.py
retinaface/widerface_evaluate/evaluation.py
retinaface/widerface_evaluate/setup.py
retinaface_py-0.0.2.dist-info/LICENSE.MIT
retinaface_py-0.0.2.dist-info/METADATA
retinaface_py-0.0.2.dist-info/WHEEL
retinaface_py-0.0.2.dist-info/top_level.txt
retinaface_py-0.0.2.dist-info/RECORD
