Metadata-Version: 2.1
Name: retinaface-py
Version: 0.0.2
Summary: RetinaFace: Single-stage Dense Face Localisation in the Wild
Home-page: https://github.com/andresprados/Pytorch_Retinaface
Author: Jiankang Deng
Maintainer: Andres Prados Torreblanca
Maintainer-email: andresprator@gmail.com
License: MIT License
Classifier: License :: OSI Approved :: MIT License
Classifier: Intended Audience :: Developers
Classifier: Intended Audience :: Science/Research
Classifier: Operating System :: OS Independent
Classifier: Programming Language :: Python
Classifier: Programming Language :: Python :: 3
Classifier: Topic :: Software Development :: Libraries
Classifier: Topic :: Software Development :: Libraries :: Python Modules
Requires-Python: >=3.6
License-File: LICENSE.MIT
Requires-Dist: numpy
Requires-Dist: torch (>=1.1.0)
Requires-Dist: torchvision (>=0.3.0)
Requires-Dist: opencv-python
